{"name":"supervisor","postlist":[{"title":"NAS安装及应用supervisor进程守护","slug":"NAS安装及应用supervisor进程守护","date":"2024-08-13T08:18:23.000Z","updated":"2024-08-13T15:26:00.815Z","comments":true,"path":"api/articles/NAS安装及应用supervisor进程守护.json","excerpt":null,"keywords":null,"cover":"https://img.carlzeng.top:3/i/2024/08/13/66bb799d6ca43.png","content":null,"raw":null,"categories":[{"name":"NAS","path":"api/categories/NAS.json"}],"tags":[{"name":"NAS","path":"api/tags/NAS.json"},{"name":"linux","path":"api/tags/linux.json"},{"name":"Python","path":"api/tags/Python.json"},{"name":"supervisor","path":"api/tags/supervisor.json"}]}]}